polyaxon_schemas/__init__.py
polyaxon_schemas/base.py
polyaxon_schemas/exceptions.py
polyaxon_schemas/logger.py
polyaxon_schemas/pod.py
polyaxon_schemas/polyaxonfile.py
polyaxon_schemas/registry.py
polyaxon_schemas/utils.py
polyaxon_schemas/api/__init__.py
polyaxon_schemas/api/authentication.py
polyaxon_schemas/api/clusters.py
polyaxon_schemas/api/code_reference.py
polyaxon_schemas/api/data.py
polyaxon_schemas/api/experiment.py
polyaxon_schemas/api/group.py
polyaxon_schemas/api/job.py
polyaxon_schemas/api/log_handler.py
polyaxon_schemas/api/project.py
polyaxon_schemas/api/user.py
polyaxon_schemas/api/version.py
polyaxon_schemas/fields/__init__.py
polyaxon_schemas/fields/dict_or_str.py
polyaxon_schemas/fields/float_or_str.py
polyaxon_schemas/fields/indexed_dict.py
polyaxon_schemas/fields/int_or_str.py
polyaxon_schemas/fields/obj_list_obj.py
polyaxon_schemas/fields/str_or_fct.py
polyaxon_schemas/fields/tensor.py
polyaxon_schemas/fields/uuids.py
polyaxon_schemas/ml/__init__.py
polyaxon_schemas/ml/bridges.py
polyaxon_schemas/ml/constraints.py
polyaxon_schemas/ml/eval.py
polyaxon_schemas/ml/fields.py
polyaxon_schemas/ml/graph.py
polyaxon_schemas/ml/hooks.py
polyaxon_schemas/ml/initializations.py
polyaxon_schemas/ml/losses.py
polyaxon_schemas/ml/metrics.py
polyaxon_schemas/ml/models.py
polyaxon_schemas/ml/optimizers.py
polyaxon_schemas/ml/regularizations.py
polyaxon_schemas/ml/train.py
polyaxon_schemas/ml/utils.py
polyaxon_schemas/ml/layers/__init__.py
polyaxon_schemas/ml/layers/advanced_activations.py
polyaxon_schemas/ml/layers/base.py
polyaxon_schemas/ml/layers/convolutional.py
polyaxon_schemas/ml/layers/convolutional_recurrent.py
polyaxon_schemas/ml/layers/core.py
polyaxon_schemas/ml/layers/embeddings.py
polyaxon_schemas/ml/layers/local.py
polyaxon_schemas/ml/layers/merge.py
polyaxon_schemas/ml/layers/noise.py
polyaxon_schemas/ml/layers/normalization.py
polyaxon_schemas/ml/layers/pooling.py
polyaxon_schemas/ml/layers/recurrent.py
polyaxon_schemas/ml/layers/wrappers.py
polyaxon_schemas-0.6.1.dist-info/LICENSE
polyaxon_schemas-0.6.1.dist-info/METADATA
polyaxon_schemas-0.6.1.dist-info/WHEEL
polyaxon_schemas-0.6.1.dist-info/top_level.txt
polyaxon_schemas-0.6.1.dist-info/RECORD
