Metadata-Version: 2.1
Name: polyaxon-schemas
Version: 0.6.1
Summary: Schema definitions and validation for Polyaxon.
Home-page: https://github.com/polyaxon/polyaxon-schemas
Author: Mourad Mourafiq
Author-email: mourad@polyaxon.com
Maintainer: Mourad Mourafiq
Maintainer-email: mourad@polyaxon.com
License: MIT
Keywords: polyaxon,tensorFlow,deep-learning,machine-learning,data-science,neural-networks,artificial-intelligence,ai,reinforcement-learning,kubernetes
Platform: any
Classifier: Programming Language :: Python
Classifier: Operating System :: OS Independent
Classifier: Intended Audience :: Developers
Classifier: Intended Audience :: Science/Research
Classifier: Topic :: Scientific/Engineering :: Artificial Intelligence
Requires-Dist: hestia (==0.6.0)
Requires-Dist: Jinja2 (~=2.10.1)
Requires-Dist: marshmallow (==3.0.0rc5)
Requires-Dist: numpy (>=1.15.2)
Requires-Dist: python-dateutil (>=2.7.3)
Requires-Dist: pytz (>=2018.9)
Requires-Dist: rhea (==0.5.5)
